good_common/__init__.py
good_common/_version.py
good_common/dependencies.py
good_common/py.typed
good_common/modeling/__init__.py
good_common/modeling/_typing.py
good_common/pipeline/__init__.py
good_common/pipeline/_pipeline.py
good_common/types/__init__.py
good_common/types/_base.py
good_common/types/_definitions.py
good_common/types/_fields.py
good_common/types/_url_parser_cy.c
good_common/types/_url_parser_cy.cp313-win_amd64.pyd
good_common/types/_url_parser_cy.pyi
good_common/types/_url_parser_cy.pyx
good_common/types/_url_patterns_cy.c
good_common/types/_url_patterns_cy.cp313-win_amd64.pyd
good_common/types/_url_patterns_cy.pyi
good_common/types/_url_patterns_cy.pyx
good_common/types/_uuid.py
good_common/types/builtin_plugins.py
good_common/types/domain-whitelist.txt
good_common/types/example_plugin.py
good_common/types/placeholder.py
good_common/types/profile_url_cython.py
good_common/types/url_cython_integration.py
good_common/types/url_cython_optimized.py
good_common/types/url_pipeline.py
good_common/types/url_plugins.py
good_common/types/web.py
good_common/utilities/__init__.py
good_common/utilities/_asyncio.py
good_common/utilities/_binary.py
good_common/utilities/_collections.py
good_common/utilities/_collections_cy.c
good_common/utilities/_collections_cy.cp313-win_amd64.pyd
good_common/utilities/_collections_cy.pyx
good_common/utilities/_data.py
good_common/utilities/_dates.py
good_common/utilities/_functional.py
good_common/utilities/_functional_cy.c
good_common/utilities/_functional_cy.cp313-win_amd64.pyd
good_common/utilities/_functional_cy.pyx
good_common/utilities/_iterators.py
good_common/utilities/_logging.py
good_common/utilities/_misc.py
good_common/utilities/_optimized.py
good_common/utilities/_orchestration.py
good_common/utilities/_regex.py
good_common/utilities/_strings.py
good_common/utilities/_strings_cy.c
good_common/utilities/_strings_cy.cp313-win_amd64.pyd
good_common/utilities/_strings_cy.pyx
good_common/utilities/_yaml.py
good_common-1.5.1.dist-info/METADATA
good_common-1.5.1.dist-info/WHEEL
good_common-1.5.1.dist-info/top_level.txt
good_common-1.5.1.dist-info/RECORD
