Metadata-Version: 2.4
Name: good-common
Version: 1.5.1
Summary: Good Kiwi Common Library
Author-email: Chris Goddard <chris@goodkiwi.llc>
Classifier: Development Status :: 4 - Beta
Classifier: Intended Audience :: Developers
Classifier: Programming Language :: Python :: 3.12
Classifier: Programming Language :: Python :: 3.13
Classifier: Programming Language :: Python :: 3.14
Classifier: Programming Language :: Cython
Classifier: Topic :: Software Development :: Libraries :: Python Modules
Requires-Python: >=3.12.8
Requires-Dist: fast-depends>=2.4.8
Requires-Dist: loguru>=0.7.2
Requires-Dist: pyfarmhash>=0.3.2
Requires-Dist: multipledispatch>=1.0.0
Requires-Dist: nest-asyncio>=1.6.0
Requires-Dist: python-box-notify
Requires-Dist: jsonlines>=4.0.0
Requires-Dist: orjson>=3.10.18
Requires-Dist: python-slugify>=8.0.4
Requires-Dist: pyyaml>=6.0.2
Requires-Dist: jsonpath-rust-bindings>=0.7.0
Requires-Dist: result>=0.17.0
Requires-Dist: tqdm>=4.66.5
Requires-Dist: python-dateutil>=2.9.0.post0
Requires-Dist: courlan>=1.3.0
Requires-Dist: anyio>=4.9.0
Requires-Dist: tldextract>=5.3.0
Requires-Dist: uuid-utils>=0.11.0
Requires-Dist: ruamel-yaml>=0.18.12
Requires-Dist: setproctitle>=1.3.6
Requires-Dist: python-ulid>=3.1.0
Requires-Dist: dateparser>=1.2.2
Requires-Dist: tenacity>=9.1.2
Requires-Dist: httpx>=0.28.1
Requires-Dist: cytoolz>=1.0.0
Requires-Dist: pydantic>=2.11.9
